{"file":"components/date_range_picker.md","objects":{"my_date_range_picker_width_examples":{"type":"deephaven.ui.Element","data":{"document":{"__dhElemName":"__main__.date_range_picker_width_examples","props":{"children":[{"__dhElemName":"deephaven.ui.components.date_range_picker.date_range_picker","props":{"children":{"__dhElemName":"deephaven.ui.components.DateRangePicker","props":{"placeholderValue":"2025-05-12T19:18:40.236291956Z","granularity":"SECOND","hideTimeZone":false,"width":"size-6000"}}}},{"__dhElemName":"deephaven.ui.components.date_range_picker.date_range_picker","props":{"children":{"__dhElemName":"deephaven.ui.components.DateRangePicker","props":{"placeholderValue":"2025-05-12T19:18:40.236601581Z","granularity":"SECOND","hideTimeZone":false,"width":"size-6000","maxWidth":"100%"}}}}]}},"state":"{}"}}}}