{"file":"components/list_view.md","objects":{"my_list_view_quiet":{"type":"deephaven.ui.Element","data":{"document":{"props":{"children":[{"__dhElemName":"deephaven.ui.components.ListView","props":{"density":"COMPACT","isQuiet":true,"overflowMode":"truncate","selectionMode":"MULTIPLE","selectedKeys":["Text 2"],"onChange":{"__dhCbid":"cb0"},"aria-label":"List View - Quiet","children":["Text 1","Text 2","Text 3"]}},{"__dhElemName":"deephaven.ui.components.ListView","props":{"density":"COMPACT","overflowMode":"truncate","selectionMode":"MULTIPLE","selectedKeys":["Text 2"],"onChange":{"__dhCbid":"cb0"},"aria-label":"List View - Default","children":["Text 1","Text 2","Text 3"]}}]},"__dhElemName":"__main__.ui_list_view_quiet"},"state":"{}"}}}}