{"file":"components/picker.md","objects":{"my_picker_section_example":{"type":"deephaven.ui.Element","data":{"document":{"props":{"align":"start","direction":"bottom","shouldFlip":true,"labelPosition":"top","children":[{"__dhElemName":"deephaven.ui.components.Section","props":{"children":[{"__dhElemName":"deephaven.ui.components.Item","props":{"children":"Option 1"}},{"__dhElemName":"deephaven.ui.components.Item","props":{"children":"Option 2"}}]}},{"__dhElemName":"deephaven.ui.components.Section","props":{"children":[{"__dhElemName":"deephaven.ui.components.Item","props":{"children":"Option 3"}},{"__dhElemName":"deephaven.ui.components.Item","props":{"children":"Option 4"}}]}}]},"__dhElemName":"deephaven.ui.components.Picker"},"state":"{}"}}}}