{"file":"components/calendar.md","objects":{"my_focused_example":{"type":"deephaven.ui.Element","data":{"document":{"props":{"children":{"__dhElemName":"deephaven.ui.components.Flex","props":{"direction":"column","alignItems":"start","gap":"size-200","flex":"auto","children":[{"__dhElemName":"deephaven.ui.components.ActionButton","props":{"type":"button","onPress":{"__dhCbid":"cb0"},"children":"Reset focused date"}},{"__dhElemName":"deephaven.ui.components.calendar.calendar","props":{"children":{"__dhElemName":"deephaven.ui.components.Calendar","props":{"focusedValue":"2021-07-01","onFocusChange":{"__dhCbid":"cb1"}}}}}]}}},"__dhElemName":"__main__.focused_example"},"state":"{}"}}}}