{"file":"components/uri.md","objects":{"t":{"type":"deephaven.ui.Element","data":{"document":{"__dhElemName":"deephaven.ui.elements.UriElement","props":{"uri":"pq://MyPersistentQuery/scope/table"}},"state":"{}"}},"p":{"type":"deephaven.ui.Element","data":{"document":{"__dhElemName":"deephaven.ui.elements.UriElement","props":{"uri":"pq://MyPersistentQuery/scope/plot"}},"state":"{}"}},"my_dashboard":{"type":"deephaven.ui.Dashboard","data":{"document":{"__dhElemName":"deephaven.ui.components.Dashboard","props":{"children":{"__dhElemName":"__main__.basic_dashboard","props":{"children":{"__dhElemName":"deephaven.ui.components.Panel","props":{"title":"Table and Plot","direction":"column","alignItems":"start","gap":"size-100","overflow":"auto","padding":"size-100","children":{"__dhElemName":"deephaven.ui.components.Flex","props":{"gap":"size-100","flex":"auto","children":[{"__dhElemName":"deephaven.ui.elements.UriElement","props":{"uri":"pq://MyPersistentQuery/scope/table"}},{"__dhElemName":"deephaven.ui.elements.UriElement","props":{"uri":"pq://MyPersistentQuery/scope/plot"}}]}}}}}}}},"state":"{}"}}}}