{"file":"components/table.md","objects":{"t":{"type":"deephaven.ui.Element","data":{"document":{"__dhElemName":"deephaven.ui.elements.UITable","props":{"table":{"__dhObid":0},"format_":[{"cols":"Size","mode":{"type":"databar","direction":"LTR"}},{"cols":"Price","mode":{"type":"databar","direction":"RTL"}}],"showQuickFilters":false,"showGroupingColumn":true,"showSearch":false,"reverse":false,"formatList":[{"cols":"Size","mode":{"type":"databar","direction":"LTR"}},{"cols":"Price","mode":{"type":"databar","direction":"RTL"}}],"f":{"cols":"Price","mode":{"type":"databar","direction":"RTL"}}}},"state":"{}"}}}}